sctram/__init__.py
sctram/__main__.py
sctram/_doctest.py
sctram/py.typed
sctram-0.0.1.dist-info/LICENSE
sctram-0.0.1.dist-info/METADATA
sctram-0.0.1.dist-info/WHEEL
sctram-0.0.1.dist-info/entry_points.txt
sctram-0.0.1.dist-info/RECORD
