Metadata-Version: 2.1
Name: sctram
Version: 0.0.1
Summary: Single Cell Trajectory Representation Metrics
Home-page: https://github.com/theislab/sctram
License: BSD-3-Clause
Author: Kemal Inecik
Author-email: k.inecik@gmail.com
Requires-Python: >=3.9,<3.13
Classifier: Development Status :: 3 - Alpha
Classifier: Intended Audience :: Developers
Classifier: Intended Audience :: Science/Research
Classifier: License :: OSI Approved :: BSD License
Classifier: Natural Language :: English
Classifier: Operating System :: MacOS :: MacOS X
Classifier: Operating System :: Microsoft :: Windows
Classifier: Operating System :: POSIX :: Linux
Classifier: Programming Language :: Python :: 3
Classifier: Programming Language :: Python :: 3.9
Classifier: Programming Language :: Python :: 3.10
Classifier: Programming Language :: Python :: 3.11
Classifier: Programming Language :: Python :: 3.12
Classifier: Topic :: Scientific/Engineering :: Bio-Informatics
Requires-Dist: PyYAML (>=5.2)
Requires-Dist: networkx (>=2.4)
Requires-Dist: numpy (>=1.17.4)
Requires-Dist: pandas (>=0.25.3)
Requires-Dist: requests (>=2.22.0)
Requires-Dist: tqdm (>=4.37.0)
Project-URL: Documentation, https://sctram.readthedocs.io
Project-URL: Repository, https://github.com/theislab/sctram
